{
    "version": "0.4.15",
    "flags": {},
    "shapes": [
        {
            "label": "streak",
            "points": [
                [
                    404.7956450525098,
                    334.97196261682257
                ],
                [
                    401.58724347239604,
                    345.68590422969464
                ],
                [
                    512.0,
                    393.1633895365644
                ],
                [
                    512.0,
                    380.31619885213485
                ],
                [
                    404.7956450525098,
                    334.97196261682257
                ]
            ],
            "shape_type": "polygon"
        },
        {
            "label": "streak",
            "points": [
                [
                    277.87590326621057,
                    141.56219288948841
                ],
                [
                    265.50476924559234,
                    140.53126505443697
                ],
                [
                    233.76760766933194,
                    369.5514018691588
                ],
                [
                    246.8517198188647,
                    372.35514018691583
                ],
                [
                    277.87590326621057,
                    141.56219288948841
                ]
            ],
            "shape_type": "polygon"
        }
    ],
    "imagePath": "1-1.jpg",
    "imageData": null,
    "imageHeight": 512,
    "imageWidth": 512,
    "text": ""
}