{
    "version": "0.4.15",
    "flags": {},
    "shapes": [
        {
            "label": "streak",
            "points": [
                [
                    286.9615384615381,
                    174.0769230769231
                ],
                [
                    274.65384615384573,
                    170.23076923076928
                ],
                [
                    223.88461538461524,
                    337.9230769230769
                ],
                [
                    238.5,
                    341.7692307692307
                ],
                [
                    286.9615384615381,
                    174.0769230769231
                ]
            ],
            "shape_type": "polygon"
        }
    ],
    "imagePath": "100-0.jpg",
    "imageData": null,
    "imageHeight": 512,
    "imageWidth": 512,
    "text": ""
}