{
    "version": "0.4.15",
    "flags": {},
    "shapes": [
        {
            "label": "streak",
            "points": [
                [
                    300.782608695652,
                    252.52173913043453
                ],
                [
                    210.3478260869565,
                    249.0434782608695
                ],
                [
                    212.9565217391305,
                    259.478260869565
                ],
                [
                    299.91304347826053,
                    262.95652173913004
                ],
                [
                    300.782608695652,
                    252.52173913043453
                ]
            ],
            "shape_type": "polygon"
        }
    ],
    "imagePath": "110-2.jpg",
    "imageData": null,
    "imageHeight": 512,
    "imageWidth": 512,
    "text": ""
}