{
    "version": "0.4.15",
    "flags": {},
    "shapes": [
        {
            "label": "streak",
            "points": [
                [
                    311.07142857142844,
                    241.13235294117658
                ],
                [
                    198.21428571428578,
                    253.98949579831924
                ],
                [
                    199.35714285714312,
                    270.6029411764707
                ],
                [
                    315.35714285714266,
                    258.27521008403346
                ],
                [
                    311.07142857142844,
                    241.13235294117658
                ]
            ],
            "shape_type": "polygon"
        },
        {
            "label": "streak",
            "points": [
                [
                    320.35714285714266,
                    196.84663865546236
                ],
                [
                    205.2394957983197,
                    200.01470588235316
                ],
                [
                    205.2394957983197,
                    217.66176470588243
                ],
                [
                    321.7857142857142,
                    213.98949579831924
                ],
                [
                    320.35714285714266,
                    196.84663865546236
                ]
            ],
            "shape_type": "polygon"
        }
    ],
    "imagePath": "12-1.jpg",
    "imageData": null,
    "imageHeight": 512,
    "imageWidth": 512,
    "text": ""
}