{
    "version": "0.4.15",
    "flags": {},
    "shapes": [
        {
            "label": "streak",
            "points": [
                [
                    512.0,
                    299.54688276651376
                ],
                [
                    512.0,
                    279.4923193016803
                ],
                [
                    0.0,
                    211.67675395659958
                ],
                [
                    0.0,
                    233.28155902550665
                ],
                [
                    512.0,
                    299.54688276651376
                ]
            ],
            "shape_type": "polygon"
        }
    ],
    "imagePath": "120-0.jpg",
    "imageData": null,
    "imageHeight": 512,
    "imageWidth": 512,
    "text": ""
}