{
    "version": "0.4.15",
    "flags": {},
    "shapes": [
        {
            "label": "streak",
            "points": [
                [
                    326.49549549549556,
                    249.6936936936936
                ],
                [
                    185.95495495495516,
                    247.89189189189165
                ],
                [
                    187.75675675675666,
                    261.4054054054054
                ],
                [
                    323.7927927927926,
                    265.0090090090089
                ],
                [
                    326.49549549549556,
                    249.6936936936936
                ]
            ],
            "shape_type": "polygon"
        }
    ],
    "imagePath": "122-3.jpg",
    "imageData": null,
    "imageHeight": 512,
    "imageWidth": 512
}