{
    "version": "0.4.15",
    "flags": {},
    "shapes": [
        {
            "label": "streak",
            "points": [
                [
                    429.57723577235765,
                    263.92682926829275
                ],
                [
                    84.86178861788585,
                    231.40650406504074
                ],
                [
                    85.67479674796732,
                    248.479674796748
                ],
                [
                    423.88617886178827,
                    280.186991869919
                ],
                [
                    429.57723577235765,
                    263.92682926829275
                ]
            ],
            "shape_type": "polygon"
        }
    ],
    "imagePath": "143-2.jpg",
    "imageData": null,
    "imageHeight": 512,
    "imageWidth": 512
}