{
    "version": "0.4.15",
    "flags": {},
    "shapes": [
        {
            "label": "streak",
            "points": [
                [
                    327.6101694915251,
                    180.36440677966084
                ],
                [
                    311.50847457627106,
                    172.7372881355932
                ],
                [
                    181.84745762711827,
                    332.906779661017
                ],
                [
                    203.03389830508468,
                    337.9915254237285
                ],
                [
                    327.6101694915251,
                    180.36440677966084
                ]
            ],
            "shape_type": "polygon"
        }
    ],
    "imagePath": "202-0.jpg",
    "imageData": null,
    "imageHeight": 512,
    "imageWidth": 512
}