{
    "version": "0.4.15",
    "flags": {},
    "shapes": [
        {
            "label": "streak",
            "points": [
                [
                    280.7497487016251,
                    261.4877282626908
                ],
                [
                    238.23006366225513,
                    237.07827944379324
                ],
                [
                    231.1434494890268,
                    250.46410621544646
                ],
                [
                    273.8767381470934,
                    274.96988607807043
                ],
                [
                    280.7497487016251,
                    261.4877282626908
                ]
            ],
            "shape_type": "polygon"
        }
    ],
    "imagePath": "216-1.jpg",
    "imageData": null,
    "imageHeight": 512,
    "imageWidth": 512,
    "text": ""
}