{
    "version": "0.4.15",
    "flags": {},
    "shapes": [
        {
            "label": "streak",
            "points": [
                [
                    237.8965517241378,
                    159.96551724137927
                ],
                [
                    224.79310344827593,
                    162.72413793103445
                ],
                [
                    273.0689655172413,
                    349.6206896551724
                ],
                [
                    288.24137931034477,
                    351.6896551724138
                ],
                [
                    237.8965517241378,
                    159.96551724137927
                ]
            ],
            "shape_type": "polygon"
        },
        {
            "label": "streak",
            "points": [
                [
                    11.689655172413723,
                    390.31034482758616
                ],
                [
                    22.72413793103442,
                    386.8620689655172
                ],
                [
                    0.0,
                    328.1924764890283
                ],
                [
                    0.0,
                    362.2351900972592
                ],
                [
                    11.689655172413723,
                    390.31034482758616
                ]
            ],
            "shape_type": "polygon"
        }
    ],
    "imagePath": "271-0.jpg",
    "imageData": null,
    "imageHeight": 512,
    "imageWidth": 512
}