{
    "version": "0.4.15",
    "flags": {},
    "shapes": [
        {
            "label": "streak",
            "points": [
                [
                    382.27027027027,
                    262.9819819819818
                ],
                [
                    273.2612612612611,
                    232.35135135135124
                ],
                [
                    267.8558558558557,
                    250.36936936936945
                ],
                [
                    380.468468468468,
                    278.2972972972975
                ],
                [
                    382.27027027027,
                    262.9819819819818
                ]
            ],
            "shape_type": "polygon"
        }
    ],
    "imagePath": "34-5.jpg",
    "imageData": null,
    "imageHeight": 512,
    "imageWidth": 512
}