{
    "version": "0.4.15",
    "flags": {},
    "shapes": [
        {
            "label": "streak",
            "points": [
                [
                    405.73404255319144,
                    250.94680851063868
                ],
                [
                    111.05319148936178,
                    244.56382978723423
                ],
                [
                    105.73404255319156,
                    260.5212765957449
                ],
                [
                    401.47872340425533,
                    267.9680851063831
                ],
                [
                    405.73404255319144,
                    250.94680851063868
                ]
            ],
            "shape_type": "polygon"
        }
    ],
    "imagePath": "50-0.jpg",
    "imageData": null,
    "imageHeight": 512,
    "imageWidth": 512
}