{
    "version": "0.4.15",
    "flags": {},
    "shapes": [
        {
            "label": "streak",
            "points": [
                [
                    284.4893048128343,
                    255.13865546218494
                ],
                [
                    230.2723453017568,
                    242.35026737967928
                ],
                [
                    227.99579831932778,
                    257.7360580595878
                ],
                [
                    281.24255156608103,
                    268.77501909854846
                ],
                [
                    284.4893048128343,
                    255.13865546218494
                ]
            ],
            "shape_type": "polygon"
        }
    ],
    "imagePath": "95-0.jpg",
    "imageData": null,
    "imageHeight": 512,
    "imageWidth": 512,
    "text": ""
}